{"Id":"6a1e16a2f1b4a13fd8bf490e","ModifyTime":1780375185,"Content":[{"Id":0,"PicAddr":"client/notice/pic/6a1e1534f1b4a13fd8bf4904.png","JumpType":"2","JumpAddr":"90066","PicType":"1","Interval":5,"BeginTime":1780354800,"EndTime":1784242800,"AppearanceDay":[],"AppearanceCondition":[],"DisappearanceCondition":[],"AppearanceTime":[]},{"Id":1,"PicAddr":"client/notice/pic/6a1e1560f1b4a13fd8bf4905.png","JumpType":"2","JumpAddr":"7219","PicType":"1","Interval":5,"BeginTime":1780354800,"EndTime":1784242800,"AppearanceDay":[],"AppearanceCondition":[],"DisappearanceCondition":[],"AppearanceTime":[]},{"Id":2,"PicAddr":"client/notice/pic/6a1e1588f1b4a13fd8bf4906.png","JumpType":"2","JumpAddr":"20020","PicType":"1","Interval":5,"BeginTime":1780354800,"EndTime":1784242800,"AppearanceDay":[],"AppearanceCondition":[],"DisappearanceCondition":[],"AppearanceTime":[]},{"Id":3,"PicAddr":"client/notice/pic/6a1e15d1f1b4a13fd8bf4908.png","JumpType":"2","JumpAddr":"20020","PicType":"1","Interval":5,"BeginTime":1780354800,"EndTime":1784242800,"AppearanceDay":[],"AppearanceCondition":[],"DisappearanceCondition":[],"AppearanceTime":[]},{"Id":4,"PicAddr":"client/notice/pic/6a1e15e8f1b4a13fd8bf4909.png","JumpType":"2","JumpAddr":"90067","PicType":"1","Interval":5,"BeginTime":1780653600,"EndTime":1784242800,"AppearanceDay":[],"AppearanceCondition":[],"DisappearanceCondition":[],"AppearanceTime":[]},{"Id":5,"PicAddr":"client/notice/pic/6a1e1609f1b4a13fd8bf490a.png","JumpType":"2","JumpAddr":"1300709","PicType":"1","Interval":5,"BeginTime":1780653600,"EndTime":1784242800,"AppearanceDay":[],"AppearanceCondition":[],"DisappearanceCondition":[],"AppearanceTime":[]},{"Id":6,"PicAddr":"client/notice/pic/6a1e1636f1b4a13fd8bf490b.png","JumpType":"2","JumpAddr":"7208","PicType":"1","Interval":5,"BeginTime":1781161200,"EndTime":1782370500,"AppearanceDay":[],"AppearanceCondition":[],"DisappearanceCondition":[],"AppearanceTime":[]},{"Id":7,"PicAddr":"client/notice/pic/6a1e165af1b4a13fd8bf490c.png","JumpType":"2","JumpAddr":"7208","PicType":"1","Interval":5,"BeginTime":1782370800,"EndTime":1783580100,"AppearanceDay":[],"AppearanceCondition":[],"DisappearanceCondition":[],"AppearanceTime":[]},{"Id":8,"PicAddr":"client/notice/pic/6a1e168bf1b4a13fd8bf490d.png","JumpType":"2","JumpAddr":"7208","PicType":"1","Interval":5,"BeginTime":1783580400,"EndTime":1784789700,"AppearanceDay":[],"AppearanceCondition":[],"DisappearanceCondition":[],"AppearanceTime":[]},{"Id":9,"PicAddr":"client/notice/pic/6a1e5e78f1b4a13fd8bf491d.png","JumpType":"2","JumpAddr":"7208","PicType":"1","Interval":5,"BeginTime":1779951600,"EndTime":1781160900,"AppearanceDay":[],"AppearanceCondition":[],"DisappearanceCondition":[],"AppearanceTime":[]}],"LoginPlatformList":[0,1,2]}